ishita_area_volume/__init__.py
ishita_area_volume/area_volume.py
ishita_area_volume-1.0.0.dist-info/METADATA
ishita_area_volume-1.0.0.dist-info/WHEEL
ishita_area_volume-1.0.0.dist-info/licenses/LICENCE.txt
ishita_area_volume-1.0.0.dist-info/RECORD
