Metadata-Version: 2.1
Name: ishita_area_volume
Version: 1.0.0
Summary: This is a python package to calculate area and volume of different shapes.
Author-email: Ishita Rathi <ishita.rathi2022@vitstudent.ac.in>
License-File: LICENCE.txt
Classifier: License :: OSI Approved :: MIT License
Classifier: Operating System :: OS Independent
Classifier: Programming Language :: Python :: 3
Requires-Python: >=3.7
